{
  "_class": "shapePath",
  "booleanOperation": -1,
  "clippingMaskMode": 0,
  "do_objectID": "93AD0A9E-21A8-4B09-A1DD-B745A4E3E43B",
  "edited": true,
  "exportOptions": {
    "_class": "exportOptions",
    "exportFormats": [
    ],
    "includedLayerIds": [
    ],
    "layerOptions": 0,
    "shouldTrim": false
  },
  "frame": {
    "_class": "rect",
    "constrainProportions": false,
    "height": 2.066256882340811,
    "width": 2.073949939997981,
    "x": 0.3027900502108014,
    "y": 0.2950586654305816
  },
  "hasClippingMask": false,
  "isClosed": true,
  "isFixedToViewport": false,
  "isFlippedHorizontal": false,
  "isFlippedVertical": false,
  "isLocked": false,
  "isVisible": true,
  "layerListExpandedType": 0,
  "name": "路径",
  "nameIsFixed": false,
  "pointRadiusBehaviour": 1,
  "points": [
    {
      "_class": "curvePoint",
      "cornerRadius": 0,
      "curveFrom": "{0.85554896167421968, 0}",
      "curveMode": 3,
      "curveTo": "{0.43901851316583923, 0}",
      "hasCurveFrom": true,
      "hasCurveTo": true,
      "point": "{0.75207004124605492, 0}"
    },
    {
      "_class": "curvePoint",
      "cornerRadius": 0,
      "curveFrom": "{0.95461263938293583, 0.35478231449967579}",
      "curveMode": 4,
      "curveTo": "{0.91949609225029105, 0.11814904728567018}",
      "hasCurveFrom": false,
      "hasCurveTo": true,
      "point": "{0.95461263938293583, 0.35478231449967579}"
    },
    {
      "_class": "curvePoint",
      "cornerRadius": 0,
      "curveFrom": "{0.96500401629752985, 0.4346846648099284}",
      "curveMode": 1,
      "curveTo": "{0.96500401629752985, 0.4346846648099284}",
      "hasCurveFrom": false,
      "hasCurveTo": false,
      "point": "{0.96500401629752985, 0.4346846648099284}"
    },
    {
      "_class": "curvePoint",
      "cornerRadius": 0,
      "curveFrom": "{0.98428596297410487, 0.62692735091178708}",
      "curveMode": 1,
      "curveTo": "{0.98428596297410487, 0.62692735091178708}",
      "hasCurveFrom": false,
      "hasCurveTo": false,
      "point": "{0.98428596297410487, 0.62692735091178708}"
    },
    {
      "_class": "curvePoint",
      "cornerRadius": 0,
      "curveFrom": "{0.99031286212858993, 0.67686048828484546}",
      "curveMode": 1,
      "curveTo": "{0.99031286212858993, 0.67686048828484546}",
      "hasCurveFrom": false,
      "hasCurveTo": false,
      "point": "{0.99031286212858993, 0.67686048828484546}"
    },
    {
      "_class": "curvePoint",
      "cornerRadius": 0,
      "curveFrom": "{1.0129244090609508, 0.79745345644609011}",
      "curveMode": 4,
      "curveTo": "{0.99670941945519997, 0.71549434633123499}",
      "hasCurveFrom": true,
      "hasCurveTo": false,
      "point": "{0.99670941945519997, 0.71549434633123499}"
    },
    {
      "_class": "curvePoint",
      "cornerRadius": 0,
      "curveFrom": "{0.8579399473837237, 0.92716643780858587}",
      "curveMode": 4,
      "curveTo": "{0.96960981205814367, 0.85922164567953474}",
      "hasCurveFrom": false,
      "hasCurveTo": true,
      "point": "{0.8579399473837237, 0.92716643780858587}"
    },
    {
      "_class": "curvePoint",
      "cornerRadius": 0,
      "curveFrom": "{0.79686461348109516, 0.96162229076432337}",
      "curveMode": 1,
      "curveTo": "{0.79686461348109516, 0.96162229076432337}",
      "hasCurveFrom": false,
      "hasCurveTo": false,
      "point": "{0.79686461348109516, 0.96162229076432337}"
    },
    {
      "_class": "curvePoint",
      "cornerRadius": 0,
      "curveFrom": "{0.72039637102278697, 1.0009759823792166}",
      "curveMode": 4,
      "curveTo": "{0.73717803977955598, 0.99236900022956431}",
      "hasCurveFrom": true,
      "hasCurveTo": false,
      "point": "{0.73717803977955598, 0.99236900022956431}"
    },
    {
      "_class": "curvePoint",
      "cornerRadius": 0,
      "curveFrom": "{0.71177635555680607, 0.99298018248931619}",
      "curveMode": 4,
      "curveTo": "{0.72012758700613633, 1.0037606140997355}",
      "hasCurveFrom": false,
      "hasCurveTo": true,
      "point": "{0.71177635555680607, 0.99298018248931619}"
    },
    {
      "_class": "curvePoint",
      "cornerRadius": 0,
      "curveFrom": "{0.61363300960346379, 0.86357264497709219}",
      "curveMode": 4,
      "curveTo": "{0.66079790732984622, 0.92385132827767225}",
      "hasCurveFrom": true,
      "hasCurveTo": false,
      "point": "{0.66079790732984622, 0.92385132827767225}"
    },
    {
      "_class": "curvePoint",
      "cornerRadius": 0,
      "curveFrom": "{0.45472431288999959, 0.7967841921538763}",
      "curveMode": 3,
      "curveTo": "{0.56121311644367367, 0.82413470427839353}",
      "hasCurveFrom": true,
      "hasCurveTo": true,
      "point": "{0.4860666181708081, 0.80483412859776637}"
    },
    {
      "_class": "curvePoint",
      "cornerRadius": 0,
      "curveFrom": "{0.37063144723249042, 0.79412273091877006}",
      "curveMode": 4,
      "curveTo": "{0.41940140732510445, 0.79373299466611891}",
      "hasCurveFrom": false,
      "hasCurveTo": true,
      "point": "{0.37063144723249042, 0.79412273091877006}"
    },
    {
      "_class": "curvePoint",
      "cornerRadius": 0,
      "curveFrom": "{0.13501042134660637, 0.80333502299962989}",
      "curveMode": 1,
      "curveTo": "{0.13501042134660637, 0.80333502299962989}",
      "hasCurveFrom": false,
      "hasCurveTo": false,
      "point": "{0.13501042134660637, 0.80333502299962989}"
    },
    {
      "_class": "curvePoint",
      "cornerRadius": 0,
      "curveFrom": "{-0.046999265886365181, 0.68444622524899268}",
      "curveMode": 4,
      "curveTo": "{0.1146137707963284, 0.8037597370281524}",
      "hasCurveFrom": true,
      "hasCurveTo": false,
      "point": "{0.1146137707963284, 0.8037597370281524}"
    },
    {
      "_class": "curvePoint",
      "cornerRadius": 0,
      "curveFrom": "{0.14543767376022043, 0.31415096036678714}",
      "curveMode": 4,
      "curveTo": "{-0.038569666134764695, 0.57510311859071206}",
      "hasCurveFrom": false,
      "hasCurveTo": true,
      "point": "{0.14543767376022043, 0.31415096036678714}"
    },
    {
      "_class": "curvePoint",
      "cornerRadius": 0,
      "curveFrom": "{0.34567870350257313, 0.03958964694000159}",
      "curveMode": 4,
      "curveTo": "{0.17773223265071716, 0.26922744081348216}",
      "hasCurveFrom": true,
      "hasCurveTo": false,
      "point": "{0.17773223265071716, 0.26922744081348216}"
    }
  ],
  "resizingConstraint": 63,
  "resizingType": 0,
  "rotation": 0,
  "shouldBreakMaskChain": false,
  "style": {
    "_class": "style",
    "blur": {
      "_class": "blur",
      "center": "{0.5, 0.5}",
      "isEnabled": false,
      "motionAngle": 0,
      "radius": 5.905384006523178,
      "saturation": 1,
      "type": 0
    },
    "borderOptions": {
      "_class": "borderOptions",
      "dashPattern": [
      ],
      "isEnabled": true,
      "lineCapStyle": 0,
      "lineJoinStyle": 0
    },
    "borders": [
    ],
    "colorControls": {
      "_class": "colorControls",
      "brightness": 0,
      "contrast": 1,
      "hue": 0,
      "isEnabled": false,
      "saturation": 1
    },
    "contextSettings": {
      "_class": "graphicsContextSettings",
      "blendMode": 0,
      "opacity": 1
    },
    "do_objectID": "82843268-2629-46A4-A3B0-D75897FEC438",
    "endMarkerType": 0,
    "fills": [
      {
        "_class": "fill",
        "color": {
          "_class": "color",
          "alpha": 1,
          "blue": 0.4513153433799744,
          "green": 0.4088624119758606,
          "red": 0.3589983582496643
        },
        "contextSettings": {
          "_class": "graphicsContextSettings",
          "blendMode": 0,
          "opacity": 1
        },
        "fillType": 0,
        "gradient": {
          "_class": "gradient",
          "elipseLength": 0,
          "from": "{0.5, 0}",
          "gradientType": 0,
          "stops": [
            {
              "_class": "gradientStop",
              "color": {
                "_class": "color",
                "alpha": 1,
                "blue": 1,
                "green": 1,
                "red": 1
              },
              "position": 0
            },
            {
              "_class": "gradientStop",
              "color": {
                "_class": "color",
                "alpha": 1,
                "blue": 0,
                "green": 0,
                "red": 0
              },
              "position": 1
            }
          ],
          "to": "{0.5, 1}"
        },
        "isEnabled": true,
        "noiseIndex": 0,
        "noiseIntensity": 0,
        "patternFillType": 1,
        "patternTileScale": 1
      }
    ],
    "innerShadows": [
    ],
    "miterLimit": 10,
    "shadows": [
    ],
    "startMarkerType": 0,
    "windingRule": 0
  }
}