{
  "_class": "shapePath",
  "booleanOperation": -1,
  "clippingMaskMode": 0,
  "do_objectID": "878E11EA-364B-4B12-8F7A-1AA555DC67B6",
  "edited": true,
  "exportOptions": {
    "_class": "exportOptions",
    "exportFormats": [
    ],
    "includedLayerIds": [
    ],
    "layerOptions": 0,
    "shouldTrim": false
  },
  "frame": {
    "_class": "rect",
    "constrainProportions": false,
    "height": 3.28539207109627,
    "width": 10.19637524370064,
    "x": 6.125777955417005,
    "y": 11.84085579473905
  },
  "hasClippingMask": false,
  "isClosed": true,
  "isFixedToViewport": false,
  "isFlippedHorizontal": false,
  "isFlippedVertical": false,
  "isLocked": false,
  "isVisible": true,
  "layerListExpandedType": 0,
  "name": "路径",
  "nameIsFixed": false,
  "pointRadiusBehaviour": 1,
  "points": [
    {
      "_class": "curvePoint",
      "cornerRadius": 0,
      "curveFrom": "{0.059509837622375529, 1}",
      "curveMode": 4,
      "curveTo": "{0.13299463160249825, 1}",
      "hasCurveFrom": true,
      "hasCurveTo": false,
      "point": "{0.13299463160249825, 1}"
    },
    {
      "_class": "curvePoint",
      "cornerRadius": 0,
      "curveFrom": "{0, 0.22390849135407437}",
      "curveMode": 2,
      "curveTo": "{-2.5466793334301197e-09, 0.7762526214468578}",
      "hasCurveFrom": true,
      "hasCurveTo": true,
      "point": "{0, 0.50005907367432878}"
    },
    {
      "_class": "curvePoint",
      "cornerRadius": 0,
      "curveFrom": "{0.13299463160249825, 0}",
      "curveMode": 4,
      "curveTo": "{0.059509840169054862, 0}",
      "hasCurveFrom": false,
      "hasCurveTo": true,
      "point": "{0.13299463160249825, 0}"
    },
    {
      "_class": "curvePoint",
      "cornerRadius": 0,
      "curveFrom": "{0.94050447216883548, 0}",
      "curveMode": 4,
      "curveTo": "{0.86707692244691403, 0}",
      "hasCurveFrom": true,
      "hasCurveTo": false,
      "point": "{0.86707692244691403, 0}"
    },
    {
      "_class": "curvePoint",
      "cornerRadius": 0,
      "curveFrom": "{1, 0.77625262144685869}",
      "curveMode": 2,
      "curveTo": "{1, 0.22390849135407437}",
      "hasCurveFrom": true,
      "hasCurveTo": true,
      "point": "{1, 0.50005907367432878}"
    },
    {
      "_class": "curvePoint",
      "cornerRadius": 0,
      "curveFrom": "{0.86707692244691403, 1}",
      "curveMode": 4,
      "curveTo": "{0.94050447216883548, 1}",
      "hasCurveFrom": false,
      "hasCurveTo": true,
      "point": "{0.86707692244691403, 1}"
    },
    {
      "_class": "curvePoint",
      "cornerRadius": 0,
      "curveFrom": "{0.13299463160249797, 1}",
      "curveMode": 1,
      "curveTo": "{0.13299463160249797, 1}",
      "hasCurveFrom": false,
      "hasCurveTo": false,
      "point": "{0.13299463160249797, 1}"
    }
  ],
  "resizingConstraint": 63,
  "resizingType": 0,
  "rotation": 0,
  "shouldBreakMaskChain": false,
  "style": {
    "_class": "style",
    "blur": {
      "_class": "blur",
      "center": "{0.5, 0.5}",
      "isEnabled": false,
      "motionAngle": 0,
      "radius": 1.465661641541039,
      "saturation": 1,
      "type": 0
    },
    "borderOptions": {
      "_class": "borderOptions",
      "dashPattern": [
      ],
      "isEnabled": true,
      "lineCapStyle": 0,
      "lineJoinStyle": 0
    },
    "borders": [
    ],
    "colorControls": {
      "_class": "colorControls",
      "brightness": 0,
      "contrast": 1,
      "hue": 0,
      "isEnabled": false,
      "saturation": 1
    },
    "contextSettings": {
      "_class": "graphicsContextSettings",
      "blendMode": 0,
      "opacity": 1
    },
    "do_objectID": "75D0CF11-28E5-41E0-963C-DF7630B42852",
    "endMarkerType": 0,
    "fills": [
    ],
    "innerShadows": [
    ],
    "miterLimit": 10,
    "shadows": [
    ],
    "startMarkerType": 0,
    "windingRule": 1
  }
}