{
  "_class": "group",
  "booleanOperation": -1,
  "clippingMaskMode": 0,
  "do_objectID": "C4E3E85B-623A-4E82-88F0-B2A4BA346D4C",
  "exportOptions": {
    "_class": "exportOptions",
    "exportFormats": [
    ],
    "includedLayerIds": [
    ],
    "layerOptions": 0,
    "shouldTrim": false
  },
  "frame": {
    "_class": "rect",
    "constrainProportions": false,
    "height": 20,
    "width": 47.0204081632653,
    "x": 0,
    "y": 10.48191539197136
  },
  "groupLayout": {
    "_class": "MSImmutableFreeformGroupLayout"
  },
  "hasClickThrough": true,
  "hasClippingMask": false,
  "isFixedToViewport": false,
  "isFlippedHorizontal": false,
  "isFlippedVertical": false,
  "isLocked": false,
  "isVisible": true,
  "layerListExpandedType": 1,
  "layers": [
    {
      "class": "shapePath",
      "id": "E97ABC9A-A3B3-413E-9000-998F0582647B"
    },
    {
      "class": "shapePath",
      "id": "32A575DB-D099-45A3-9469-F1C99C353DB7"
    },
    {
      "class": "shapePath",
      "id": "69EC0606-A1D0-48F3-A1E3-B9C814E3D975"
    },
    {
      "class": "shapePath",
      "id": "B21C625B-B499-47E7-96A3-B3B98F4F8C3D"
    },
    {
      "class": "shapePath",
      "id": "F01C37D6-AC22-4FD0-81D6-A0276920F22D"
    },
    {
      "class": "shapePath",
      "id": "E068BEBB-1865-4211-B10F-825F8AFB06C3"
    },
    {
      "class": "shapePath",
      "id": "B15227F6-D51A-4CFE-AB58-3F7A61E23424"
    },
    {
      "class": "shapePath",
      "id": "34A9986A-2BAE-4589-B965-F859CBB3D99A"
    },
    {
      "class": "shapePath",
      "id": "DE964F3B-7030-485D-BF96-33B71E53C180"
    },
    {
      "class": "shapePath",
      "id": "A5EE0368-321F-4C78-B9ED-3978A194C367"
    },
    {
      "class": "shapePath",
      "id": "B143165F-03AE-42F2-94B9-6BF94116ADEC"
    },
    {
      "class": "shapePath",
      "id": "683879E6-2026-4432-B7C4-97D990F39F65"
    },
    {
      "class": "shapePath",
      "id": "8C9BB36E-5DF2-4844-A82B-FFAAAEE1B483"
    },
    {
      "class": "shapePath",
      "id": "C12A08C9-A2FF-437A-A5B4-3165715D7A36"
    },
    {
      "class": "shapePath",
      "id": "F530ABDE-CFA3-49EA-A529-01869C96D68E"
    },
    {
      "class": "shapePath",
      "id": "05B8F1D6-5C3B-4E4A-B107-9E96C515F9C7"
    },
    {
      "class": "shapePath",
      "id": "FDB3C971-EF5E-427C-8577-A3E4DADE3409"
    },
    {
      "class": "shapePath",
      "id": "25F83163-1085-4D2D-9839-F54D2CC6322A"
    },
    {
      "class": "shapePath",
      "id": "CEF4580B-00E2-46A3-BEAD-3BD7BCE60318"
    },
    {
      "class": "shapePath",
      "id": "666141D5-5AFA-4FDE-AC25-46295FFAE2F6"
    },
    {
      "class": "shapePath",
      "id": "ED351B0C-19EC-4AAF-9F77-952E2159208E"
    },
    {
      "class": "shapePath",
      "id": "D14C5541-C375-47F7-92A6-FE8A4DFEDDC5"
    },
    {
      "class": "shapePath",
      "id": "A1E65932-89BC-426D-8AED-AC648EC42E21"
    },
    {
      "class": "shapePath",
      "id": "99EA539E-D04D-4EC4-95C0-049FFA7C4967"
    },
    {
      "class": "shapePath",
      "id": "8E964901-8E73-4E91-9631-2EB876FA3382"
    },
    {
      "class": "shapePath",
      "id": "0335A160-D23B-4B2E-828C-390EFE4EEEC5"
    },
    {
      "class": "shapePath",
      "id": "B565461F-B272-4811-88D0-83A0B8213906"
    },
    {
      "class": "shapePath",
      "id": "3195B05B-B3F5-4664-A725-58B6D7D8256C"
    },
    {
      "class": "shapePath",
      "id": "AA685D39-8CFA-4C25-A079-D8968CA4A163"
    },
    {
      "class": "shapePath",
      "id": "DF9B9E0D-CF88-4040-82C6-5CEABCEC68D8"
    },
    {
      "class": "shapePath",
      "id": "F4089D44-E7C7-4ADD-8669-98478AD2E43D"
    },
    {
      "class": "shapePath",
      "id": "2B644CFD-7F40-4AD0-8FB0-C4DF136782A9"
    },
    {
      "class": "shapePath",
      "id": "266A595C-DE29-447A-B29B-27DBD3A7DD06"
    },
    {
      "class": "shapePath",
      "id": "CEE909DD-B00E-4D04-87D6-09413D00EA77"
    },
    {
      "class": "shapePath",
      "id": "73AD3D59-92F7-4866-9D95-C0D655CCBBBC"
    },
    {
      "class": "shapePath",
      "id": "060F22D6-6B1F-479D-BAD6-0AC3EA355FBD"
    },
    {
      "class": "shapePath",
      "id": "1AFF748D-BAD6-44BE-BB3A-6B6B08EA122F"
    },
    {
      "class": "shapePath",
      "id": "C4A4DFFE-6F56-4878-8B9A-8A3691AC7446"
    },
    {
      "class": "shapePath",
      "id": "A8D81D42-92CA-4962-ACC4-0E0D0212EB82"
    },
    {
      "class": "shapePath",
      "id": "08EEA02B-2094-4908-803D-FEC12D085871"
    },
    {
      "class": "shapePath",
      "id": "D5C762D5-C88C-4AEE-876F-5DCDFF6389AA"
    }
  ],
  "name": "Down",
  "nameIsFixed": true,
  "resizingConstraint": 63,
  "resizingType": 0,
  "rotation": 0,
  "shouldBreakMaskChain": false,
  "style": {
    "_class": "style",
    "blur": {
      "_class": "blur",
      "center": "{0.5, 0.5}",
      "isEnabled": false,
      "motionAngle": 0,
      "radius": 11.00000023841858,
      "saturation": 1,
      "type": 0
    },
    "borderOptions": {
      "_class": "borderOptions",
      "dashPattern": [
      ],
      "isEnabled": true,
      "lineCapStyle": 0,
      "lineJoinStyle": 0
    },
    "borders": [
    ],
    "colorControls": {
      "_class": "colorControls",
      "brightness": 0,
      "contrast": 1,
      "hue": 0,
      "isEnabled": false,
      "saturation": 1
    },
    "contextSettings": {
      "_class": "graphicsContextSettings",
      "blendMode": 0,
      "opacity": 1
    },
    "do_objectID": "E476B2ED-B574-43F7-ACCC-DE53C0B18085",
    "endMarkerType": 0,
    "fills": [
    ],
    "innerShadows": [
    ],
    "miterLimit": 10,
    "shadows": [
    ],
    "startMarkerType": 0,
    "windingRule": 1
  }
}