{
  "_class": "shapePath",
  "booleanOperation": -1,
  "clippingMaskMode": 0,
  "do_objectID": "83A1A972-25C0-407D-8613-9B37A24919B2",
  "edited": true,
  "exportOptions": {
    "_class": "exportOptions",
    "exportFormats": [
    ],
    "includedLayerIds": [
    ],
    "layerOptions": 0,
    "shouldTrim": false
  },
  "frame": {
    "_class": "rect",
    "constrainProportions": false,
    "height": 2.643582276702131,
    "width": 5.674262166856737,
    "x": 0.3396229338329704,
    "y": 0.3749999999999414
  },
  "hasClippingMask": false,
  "isClosed": true,
  "isFixedToViewport": false,
  "isFlippedHorizontal": false,
  "isFlippedVertical": false,
  "isLocked": false,
  "isVisible": true,
  "layerListExpandedType": 0,
  "name": "路径",
  "nameIsFixed": false,
  "pointRadiusBehaviour": 1,
  "points": [
    {
      "_class": "curvePoint",
      "cornerRadius": 0,
      "curveFrom": "{0.71131865971793762, 0.013844936183291648}",
      "curveMode": 4,
      "curveTo": "{0.57506143057950787, 0.0018060202895530328}",
      "hasCurveFrom": true,
      "hasCurveTo": false,
      "point": "{0.57506143057950787, 0.0018060202895530328}"
    },
    {
      "_class": "curvePoint",
      "cornerRadius": 0,
      "curveFrom": "{0.92759176590562087, 0.21808582374418506}",
      "curveMode": 4,
      "curveTo": "{0.82864760549606953, 0.086060140996477116}",
      "hasCurveFrom": false,
      "hasCurveTo": true,
      "point": "{0.92759176590562087, 0.21808582374418506}"
    },
    {
      "_class": "curvePoint",
      "cornerRadius": 0,
      "curveFrom": "{0.94896820027041884, 0.24852640517001962}",
      "curveMode": 1,
      "curveTo": "{0.94896820027041884, 0.24852640517001962}",
      "hasCurveFrom": false,
      "hasCurveTo": false,
      "point": "{0.94896820027041884, 0.24852640517001962}"
    },
    {
      "_class": "curvePoint",
      "cornerRadius": 0,
      "curveFrom": "{0.95264623426437733, 0.26605632627793624}",
      "curveMode": 4,
      "curveTo": "{0.94534477079153645, 0.22930727424096348}",
      "hasCurveFrom": true,
      "hasCurveTo": false,
      "point": "{0.94534477079153645, 0.22930727424096348}"
    },
    {
      "_class": "curvePoint",
      "cornerRadius": 0,
      "curveFrom": "{0.96501015969706871, 0.33332536658798417}",
      "curveMode": 4,
      "curveTo": "{0.95919769078494421, 0.30075277909041986}",
      "hasCurveFrom": false,
      "hasCurveTo": true,
      "point": "{0.96501015969706871, 0.33332536658798417}"
    },
    {
      "_class": "curvePoint",
      "cornerRadius": 0,
      "curveFrom": "{0.99762367510823735, 0.53761463015466926}",
      "curveMode": 4,
      "curveTo": "{0.98024162295194883, 0.42460026704548853}",
      "hasCurveFrom": true,
      "hasCurveTo": false,
      "point": "{0.98024162295194883, 0.42460026704548853}"
    },
    {
      "_class": "curvePoint",
      "cornerRadius": 0,
      "curveFrom": "{0.97798750993126526, 0.80165324167812602}",
      "curveMode": 3,
      "curveTo": "{1.0033582350307562, 0.61550689077825205}",
      "hasCurveFrom": true,
      "hasCurveTo": true,
      "point": "{0.9981505407247242, 0.65371601912867872}"
    },
    {
      "_class": "curvePoint",
      "cornerRadius": 0,
      "curveFrom": "{0.76146051466752818, 0.98989152490496579}",
      "curveMode": 3,
      "curveTo": "{0.88453092381973697, 0.98989152490496579}",
      "hasCurveFrom": true,
      "hasCurveTo": true,
      "point": "{0.79645582080843202, 0.98989152490496579}"
    },
    {
      "_class": "curvePoint",
      "cornerRadius": 0,
      "curveFrom": "{0.72823521058332208, 0.95300178040530625}",
      "curveMode": 4,
      "curveTo": "{0.74809366738318195, 0.98096754606960734}",
      "hasCurveFrom": false,
      "hasCurveTo": true,
      "point": "{0.72823521058332208, 0.95300178040530625}"
    },
    {
      "_class": "curvePoint",
      "cornerRadius": 0,
      "curveFrom": "{0.66651602832290668, 0.87054654449050983}",
      "curveMode": 4,
      "curveTo": "{0.71000085205118046, 0.92755806440932331}",
      "hasCurveFrom": true,
      "hasCurveTo": false,
      "point": "{0.71000085205118046, 0.92755806440932331}"
    },
    {
      "_class": "curvePoint",
      "cornerRadius": 0,
      "curveFrom": "{0.43048026738133838, 0.84435376899722281}",
      "curveMode": 3,
      "curveTo": "{0.6109116336737721, 0.84435376899722281}",
      "hasCurveFrom": true,
      "hasCurveTo": true,
      "point": "{0.50305740330865922, 0.84435376899722281}"
    },
    {
      "_class": "curvePoint",
      "cornerRadius": 0,
      "curveFrom": "{0.33100929903619702, 0.90931006354838206}",
      "curveMode": 4,
      "curveTo": "{0.37911988441221367, 0.86598518307576478}",
      "hasCurveFrom": false,
      "hasCurveTo": true,
      "point": "{0.33100929903619702, 0.90931006354838206}"
    },
    {
      "_class": "curvePoint",
      "cornerRadius": 0,
      "curveFrom": "{0.30406267308186125, 0.9361717913977865}",
      "curveMode": 1,
      "curveTo": "{0.30406267308186125, 0.9361717913977865}",
      "hasCurveFrom": false,
      "hasCurveTo": false,
      "point": "{0.30406267308186125, 0.9361717913977865}"
    },
    {
      "_class": "curvePoint",
      "cornerRadius": 0,
      "curveFrom": "{0.27061870765737445, 0.97260516326221635}",
      "curveMode": 4,
      "curveTo": "{0.2734987628943506, 0.96951847264769631}",
      "hasCurveFrom": true,
      "hasCurveTo": false,
      "point": "{0.2734987628943506, 0.96951847264769631}"
    },
    {
      "_class": "curvePoint",
      "cornerRadius": 0,
      "curveFrom": "{0.23033611701775678, 1.0124723528872954}",
      "curveMode": 3,
      "curveTo": "{0.26827171319056553, 0.97507169000656613}",
      "hasCurveFrom": true,
      "hasCurveTo": true,
      "point": "{0.2668188620028053, 0.97650405440758281}"
    },
    {
      "_class": "curvePoint",
      "cornerRadius": 0,
      "curveFrom": "{0.13035511585967227, 0.94798536112747622}",
      "curveMode": 4,
      "curveTo": "{0.19972172101738581, 1.0102672745183041}",
      "hasCurveFrom": false,
      "hasCurveTo": true,
      "point": "{0.13035511585967227, 0.94798536112747622}"
    },
    {
      "_class": "curvePoint",
      "cornerRadius": 0,
      "curveFrom": "{0.021437013369916456, 0.82876448122980828}",
      "curveMode": 4,
      "curveTo": "{0.11432765902401061, 0.93194820780214138}",
      "hasCurveFrom": true,
      "hasCurveTo": false,
      "point": "{0.11432765902401061, 0.93194820780214138}"
    },
    {
      "_class": "curvePoint",
      "cornerRadius": 0,
      "curveFrom": "{0.015812147772315478, 0.22835685926524643}",
      "curveMode": 4,
      "curveTo": "{-0.012461051310383076, 0.59996769845078435}",
      "hasCurveFrom": false,
      "hasCurveTo": true,
      "point": "{0.015812147772315478, 0.22835685926524643}"
    },
    {
      "_class": "curvePoint",
      "cornerRadius": 0,
      "curveFrom": "{0.017669061042501398, 0.20455198416390613}",
      "curveMode": 1,
      "curveTo": "{0.017669061042501398, 0.20455198416390613}",
      "hasCurveFrom": false,
      "hasCurveTo": false,
      "point": "{0.017669061042501398, 0.20455198416390613}"
    },
    {
      "_class": "curvePoint",
      "cornerRadius": 0,
      "curveFrom": "{0.18520570517685428, 0.072595879225350143}",
      "curveMode": 4,
      "curveTo": "{0, 0.21814185894849558}",
      "hasCurveFrom": true,
      "hasCurveTo": false,
      "point": "{0, 0.21814185894849558}"
    },
    {
      "_class": "curvePoint",
      "cornerRadius": 0,
      "curveFrom": "{0.53361586983917908, 0}",
      "curveMode": 4,
      "curveTo": "{0.36304631464641945, 0}",
      "hasCurveFrom": false,
      "hasCurveTo": true,
      "point": "{0.53361586983917908, 0}"
    }
  ],
  "resizingConstraint": 63,
  "resizingType": 0,
  "rotation": 0,
  "shouldBreakMaskChain": false,
  "style": {
    "_class": "style",
    "blur": {
      "_class": "blur",
      "center": "{0.5, 0.5}",
      "isEnabled": false,
      "motionAngle": 0,
      "radius": 7.516977911446965,
      "saturation": 1,
      "type": 0
    },
    "borderOptions": {
      "_class": "borderOptions",
      "dashPattern": [
      ],
      "isEnabled": true,
      "lineCapStyle": 0,
      "lineJoinStyle": 0
    },
    "borders": [
    ],
    "colorControls": {
      "_class": "colorControls",
      "brightness": 0,
      "contrast": 1,
      "hue": 0,
      "isEnabled": false,
      "saturation": 1
    },
    "contextSettings": {
      "_class": "graphicsContextSettings",
      "blendMode": 0,
      "opacity": 1
    },
    "do_objectID": "86B4513F-AE75-4FE9-96D7-E7E165949C34",
    "endMarkerType": 0,
    "fills": [
      {
        "_class": "fill",
        "color": {
          "_class": "color",
          "alpha": 1,
          "blue": 0.4513153433799744,
          "green": 0.4088624119758606,
          "red": 0.3589983582496643
        },
        "contextSettings": {
          "_class": "graphicsContextSettings",
          "blendMode": 0,
          "opacity": 1
        },
        "fillType": 0,
        "gradient": {
          "_class": "gradient",
          "elipseLength": 0,
          "from": "{0.5, 0}",
          "gradientType": 0,
          "stops": [
            {
              "_class": "gradientStop",
              "color": {
                "_class": "color",
                "alpha": 1,
                "blue": 1,
                "green": 1,
                "red": 1
              },
              "position": 0
            },
            {
              "_class": "gradientStop",
              "color": {
                "_class": "color",
                "alpha": 1,
                "blue": 0,
                "green": 0,
                "red": 0
              },
              "position": 1
            }
          ],
          "to": "{0.5, 1}"
        },
        "isEnabled": true,
        "noiseIndex": 0,
        "noiseIntensity": 0,
        "patternFillType": 1,
        "patternTileScale": 1
      }
    ],
    "innerShadows": [
    ],
    "miterLimit": 10,
    "shadows": [
    ],
    "startMarkerType": 0,
    "windingRule": 0
  }
}